spoofagent/__init__.py
spoofagent/user_agent_generator.py
spoofagent-1.0.1.dist-info/LICENSE
spoofagent-1.0.1.dist-info/METADATA
spoofagent-1.0.1.dist-info/WHEEL
spoofagent-1.0.1.dist-info/top_level.txt
spoofagent-1.0.1.dist-info/RECORD
