Metadata-Version: 2.1
Name: spoofagent
Version: 1.0.1
Summary: A simple library to generate fake user agents.
Home-page: https://github.com/VampXDH/useragent-generator
Author: VampXD
Author-email: bagasmuhammadriszki2@gmail.com
Classifier: Programming Language :: Python :: 3
Classifier: License :: OSI Approved :: MIT License
Classifier: Operating System :: OS Independent
Requires-Python: >=3.6
License-File: LICENSE
